{
  "dockerfilePath": "Dockerfile",
  "buildDir": "",
  "containerPort": 80,
  "envParams": {
    "MYSQL_ADDRESS": "${MYSQL_ADDRESS}",
    "MYSQL_USERNAME": "${MYSQL_USERNAME}",
    "MYSQL_PASSWORD": "${MYSQL_PASSWORD}",
    "REDIS_ADDRESS": "${REDIS_ADDRESS}",
    "REDIS_PASSWORD": "${REDIS_PASSWORD}",
    "PORT": "80"
  },
  "cpu": 1,
  "mem": 2,
  "policyType": "cpu",
  "policyThreshold": 60,
  "customLogs": "stdout",
  "initialDelaySeconds": 60,
  "minNum": 1,
  "maxNum": 50,
  "remark": "鏅烘収鍦颁骇鎴夸骇灏忕▼搴忔湇鍔＄",
  "healthCheckConfig": {
    "livenessConfig": {
      "path": "/api/health",
      "port": 80
    },
    "readinessConfig": {
      "path": "/api/health",
      "port": 80
    }
  }
}
